bottle_agamemnon.py
setup.py
bottle_agamemnon.egg-info/PKG-INFO
bottle_agamemnon.egg-info/SOURCES.txt
bottle_agamemnon.egg-info/dependency_links.txt
bottle_agamemnon.egg-info/requires.txt
bottle_agamemnon.egg-info/top_level.txt