Metadata-Version: 1.0
Name: bottle-agamemnon
Version: 0.1.0
Summary: Agamemnon integration for bottle
Home-page: http://github.com/turtlebender/bottle-agamemnon/
Author: Tom Howe
Author-email: turtlebender@gmail.com
License: MIT
Platform: any
Classifier: Environment :: Web Environment
Classifier: Intended Audience :: Developers
Classifier: License :: OSI Approved :: MIT License
Classifier: Operating System :: OS Independent
Classifier: Programming Language :: Python
Classifier: Topic :: Internet :: WWW/HTTP :: Dynamic Content
Classifier: Topic :: Software Development :: Libraries :: Python Modules
